doppler.py
setup.py
doppler.egg-info/PKG-INFO
doppler.egg-info/SOURCES.txt
doppler.egg-info/dependency_links.txt
doppler.egg-info/entry_points.txt
doppler.egg-info/requires.txt
doppler.egg-info/top_level.txt
doppler.egg-info/zip-safe