Metadata-Version: 1.0
Name: doppler
Version: 0.2
Summary: A raw SQL migration toolfor managing your database without an ORM.
Home-page: http://github.com/nickgartmann/doppler/
Author: Nick Gartmann
Author-email: nick@rokkincat.com
License: BSD
Platform: any
Classifier: Intended Audience :: Developers
Classifier: License :: OSI Approved :: BSD License
Classifier: Operating System :: OS Independent
Classifier: Programming Language :: Python
